{
	"$schema": "https://raw.githubusercontent.com/xen-42/outer-wilds-new-horizons/main/NewHorizons/Schemas/body_schema.json",
	"name": "Center Offset",
	"starSystem": "CantAffordaName.ArchipelagoSystem",
	"Atmosphere": {
		"size": 1000.0
	},
	"Base": {
		"centerOfSolarSystem": true,
		"gravityFallOff": "linear",
		"invulnerableToSun": true,
		"surfaceGravity": 15.0,
		"surfaceSize": 600.0
	},
	"Orbit": {
		"isStatic": true
	},
	"ReferenceFrame": {
		"maxTargetDistance": -1.0
	},
	"ShipLog": {
		"mapMode": {}
	},
	"ShockEffect": {}
}